apt_info_mcp/__init__.py
apt_info_mcp/__main__.py
apt_info_mcp/db.py
apt_info_mcp/search.py
apt_info_mcp/utils.py
apt_info_mcp-0.1.0.dist-info/METADATA
apt_info_mcp-0.1.0.dist-info/WHEEL
apt_info_mcp-0.1.0.dist-info/entry_points.txt
apt_info_mcp-0.1.0.dist-info/RECORD
