Metadata-Version: 2.4
Name: apt-info-mcp
Version: 0.1.0
Summary: 아파트 실거래가 및 정보 조회 MCP 서버
Requires-Python: >=3.10
Requires-Dist: mcp[cli]
Requires-Dist: python-dotenv
Requires-Dist: supabase
